goat_plugins/erc20/__init__.py
goat_plugins/erc20/abi.py
goat_plugins/erc20/parameters.py
goat_plugins/erc20/service.py
goat_plugins/erc20/token.py
goat_sdk_plugin_erc20-0.1.2.dist-info/METADATA
goat_sdk_plugin_erc20-0.1.2.dist-info/WHEEL
goat_sdk_plugin_erc20-0.1.2.dist-info/RECORD
